odoo/addons/partner_supplierinfo/README.rst
odoo/addons/partner_supplierinfo/__init__.py
odoo/addons/partner_supplierinfo/__manifest__.py
odoo/addons/partner_supplierinfo/i18n/es.po
odoo/addons/partner_supplierinfo/i18n/partner_supplierinfo.pot
odoo/addons/partner_supplierinfo/models/__init__.py
odoo/addons/partner_supplierinfo/models/partner_supplierinfo.py
odoo/addons/partner_supplierinfo/models/res_partner.py
odoo/addons/partner_supplierinfo/readme/CONTRIBUTORS.rst
odoo/addons/partner_supplierinfo/readme/DESCRIPTION.rst
odoo/addons/partner_supplierinfo/readme/ROADMAP.rst
odoo/addons/partner_supplierinfo/readme/USAGE.rst
odoo/addons/partner_supplierinfo/security/ir.model.access.csv
odoo/addons/partner_supplierinfo/static/description/icon.png
odoo/addons/partner_supplierinfo/static/description/index.html
odoo/addons/partner_supplierinfo/tests/__init__.py
odoo/addons/partner_supplierinfo/tests/test_partner_supplierinfo.py
odoo/addons/partner_supplierinfo/views/res_partner_view.xml
odoo_addon_partner_supplierinfo-15.0.1.0.0.4.dist-info/METADATA
odoo_addon_partner_supplierinfo-15.0.1.0.0.4.dist-info/WHEEL
odoo_addon_partner_supplierinfo-15.0.1.0.0.4.dist-info/top_level.txt
odoo_addon_partner_supplierinfo-15.0.1.0.0.4.dist-info/RECORD
